{
    "swagger": "2.0",
    "info": {
        "title": "dealenroute api",
        "version": "1.0.0"
    },
    "basePath": "/dealenroute/api/v1",
    "paths": {
        "/register/user": {
            "post": {
                "summary": "register user",
                "operationId": "create",
                "parameters": [
                    {
                        "name": "first_name",
                        "in": "query",
                        "required": true,
                        "type": "string"
                    },
                    {
                        "name": "last_name",
                        "in": "query",
                        "required": true,
                        "type": "string"
                    },
                    {
                        "name": "email",
                        "in": "query",
                        "required": true,
                        "type": "string"
                    },
                    {
                        "name": "phone",
                        "in": "query",
                        "required": true,
                        "type": "string"
                    },
                    {
                        "name": "device_token",
                        "in": "query",
                        "required": true,
                        "type": "string"
                    },
                    {
                        "name": "password",
                        "in": "query",
                        "required": true,
                        "type": "string"
                    }
                ],
                "responses": {
                    "200": {
                        "description": "successful operation"
                    }
                }
            }
        }
    },
    "definitions": {}
}